MANIFEST.in
README.md
setup.py
pygtk_form/__init__.py
pygtk_form.egg-info/PKG-INFO
pygtk_form.egg-info/SOURCES.txt
pygtk_form.egg-info/dependency_links.txt
pygtk_form.egg-info/top_level.txt
pygtk_form/fields/__init__.py
pygtk_form/fields/colorchooserfield.py
pygtk_form/fields/comboboxfield.py
pygtk_form/fields/filechooserfield.py
pygtk_form/fields/textfield.py
pygtk_form/fields/togglefield.py
pygtk_form/res/css/default.css
pygtk_form/res/css/windows_dark.css
pygtk_form/res/css/windows_light.css