Metadata-Version: 2.1
Name: pygtk-form
Version: 0.0.3
Summary: Create forms very easily for your scripts with GTK !
Home-page: https://github.com/cestoliv/pygtk_form
Author: Olivier Cartier
Author-email: cestoliv@chevro.fr
License: UNKNOWN
Platform: UNKNOWN
Requires-Python: >=3.6
